abuseACL/__init__.py
abuseACL/__main__.py
abuseACL/core/Logger.py
abuseACL/core/__init__.py
abuseACL/core/abuseACL.py
abuseACL/network/Kerberos.py
abuseACL/network/LDAP.py
abuseACL/network/__init__.py
abuseACL/structures/Credentials.py
abuseACL/structures/Target.py
abuseACL/structures/__init__.py
abuseACL/structures/sAMAccountType.py
abuseACL/structures/structures.py
abuseACL/structures/ADObject/ADAdminSDHolder.py
abuseACL/structures/ADObject/ADCertificateTemplate.py
abuseACL/structures/ADObject/ADComputer.py
abuseACL/structures/ADObject/ADContainer.py
abuseACL/structures/ADObject/ADDomain.py
abuseACL/structures/ADObject/ADGPO.py
abuseACL/structures/ADObject/ADGroup.py
abuseACL/structures/ADObject/ADOU.py
abuseACL/structures/ADObject/ADSchema.py
abuseACL/structures/ADObject/ADUser.py
abuseACL/structures/ADObject/ADgMSA.py
abuseACL/structures/ADObject/__init__.py
abuseacl-2.0.1.data/data/requirements.txt
abuseacl-2.0.1.dist-info/licenses/LICENSE
abuseacl-2.0.1.dist-info/METADATA
abuseacl-2.0.1.dist-info/WHEEL
abuseacl-2.0.1.dist-info/entry_points.txt
abuseacl-2.0.1.dist-info/top_level.txt
abuseacl-2.0.1.dist-info/RECORD
