Metadata-Version: 2.4
Name: abuseACL
Version: 2.0.1
Summary: List vulnerable ACL.
Home-page: https://github.com/AetherBlack/abuseACL
Author: Aether
License: MIT
Project-URL: Bug Tracker, https://github.com/AetherBlack/abuseACL/issues
Keywords: abuseACL ActiveDirectory AD
Classifier: Intended Audience :: Information Technology
Classifier: Programming Language :: Python :: 3
Requires-Python: >=3.6, <4
License-File: LICENSE
Requires-Dist: impacket
Requires-Dist: colorama
Requires-Dist: pycryptodome
Dynamic: author
Dynamic: classifier
Dynamic: description
Dynamic: description-content-type
Dynamic: home-page
Dynamic: keywords
Dynamic: license-file
Dynamic: requires-dist
Dynamic: requires-python
Dynamic: summary
